{
  "title": "Estado plurinacional",
  "href": "https://plataforma.chileconvencion.cl/m/iniciativa_popular/o/56750",
  "supporters": 2,
  "id": 56750,
  "category": "estado",
  "topic": "Autonomías territoriales e indígenas",
  "outline": [
    [
      "Problema a Solucionar:",
      "Crear una propia autonomía indígena ,estado plurinacional, reconocimiento territorial y reivindicación mapuche"
    ],
    [
      "Situación Ideal:",
      "Reivindicación indígena ,cultura,control territorial, preservación de lengua materna.\nFormación de un partido político indígena"
    ],
    [
      "Qué debe Contemplar la Nueva Constitución:",
      "Creación de un partido político u orgnanismo que representa alos pueblos originarios."
    ],
    [
      "¿Con qué argumentos tú o tu organización respaldan esta propuesta?",
      "Estados plurinacional como en España (catalán),Bolivia,Noruega,Nueva Zelanda."
    ],
    [
      "Propuesta de articulado",
      "Creación de un estado plurinacional, y reconocimiento de un partido político indígena"
    ],
    [
      "Breve reseña sobre quién o quiénes proponen y la historia de la elaboración de la iniciativa",
      "Héctor llaitul"
    ]
  ]
}